<?xml version="1.0" encoding="UTF-8" standalone="yes"?>
<root xmlns:xsi="http://www.w3.org/2001/XMLSchema-instance">
	<Anim>
		<id_i>1</id_i>
		<ySwing>0.3</ySwing>
		<yRate>20</yRate>
	</Anim>
	<Anim>
		<id_i>2</id_i>
		<ySwing>0.4</ySwing>
		<yRate>25</yRate>
	</Anim>
	<Anim>
		<id_i>3</id_i>
		<xSwing>0.4</xSwing>
		<xRate>15</xRate>
	</Anim>
	<Anim>
		<id_i>4</id_i>
		<ySwing>0.4</ySwing>
		<yRate>25</yRate>
		<zSwing>1</zSwing>
		<zRate>15</zRate>
	</Anim>
	<Anim>
		<id_i>5</id_i>
		<ySwing>0.3</ySwing>
		<yRate>20</yRate>
	</Anim>
	<Anim>
		<id_i>6</id_i>
		<ySwing>0.4</ySwing>
		<yRate>25</yRate>
	</Anim>
	<Anim>
		<id_i>7</id_i>
		<ySwing>0.1</ySwing>
		<yRate>15</yRate>
	</Anim>
	<Anim>
		<id_i>8</id_i>
		<ySwing>0.1</ySwing>
		<yRate>20</yRate>
	</Anim>
</root>